graphics_planes/GraphicsPlaneModule.py
graphics_planes/PlaneModule.py
graphics_planes/ShapeModule.py
graphics_planes/__init__.py
graphis_planes/__init__.py
graphis_planes/modulo.py
graphis_planes/modulo2.py
graphics_planes-1.0.2.dist-info/METADATA
graphics_planes-1.0.2.dist-info/WHEEL
graphics_planes-1.0.2.dist-info/top_level.txt
graphics_planes-1.0.2.dist-info/RECORD
