Metadata-Version: 2.1
Name: graphics_planes
Version: 1.0.2
Summary: Esta es una libreria para generar graficos en 2D, añadiendo herramientas y utilidades extras para mejorar la generacion de graficos.
Home-page: https://github.com/CCFTS/graphics-plane
Author: Damian Zsiros
Author-email: damjeronzalez23@gmail.com
Maintainer: Alejandro Beltran, Cristian Cuadrado
Classifier: Programming Language :: Python :: 3
Classifier: License :: OSI Approved :: MIT License
Requires-Python: >=3.6
Requires-Dist: setuptools ==74.0.0
Requires-Dist: twine ==5.1.1
Requires-Dist: svg-turtle ==0.4.2
Requires-Dist: svgwrite ==1.4.3
Requires-Dist: PythonTurtle ==0.3.2
